odoo/addons/ssi_telegram/README.rst
odoo/addons/ssi_telegram/__init__.py
odoo/addons/ssi_telegram/__manifest__.py
odoo/addons/ssi_telegram/menu.xml
odoo/addons/ssi_telegram/data/ir_sequence_data.xml
odoo/addons/ssi_telegram/data/sequence_template_data.xml
odoo/addons/ssi_telegram/models/__init__.py
odoo/addons/ssi_telegram/models/res_company.py
odoo/addons/ssi_telegram/models/res_partner.py
odoo/addons/ssi_telegram/models/telegram_backend.py
odoo/addons/ssi_telegram/models/telegram_backend_chat.py
odoo/addons/ssi_telegram/security/ir.model.access.csv
odoo/addons/ssi_telegram/static/description/icon.png
odoo/addons/ssi_telegram/views/res_company_views.xml
odoo/addons/ssi_telegram/views/res_partner_views.xml
odoo/addons/ssi_telegram/views/telegram_backend_chat_views.xml
odoo/addons/ssi_telegram/views/telegram_backend_views.xml
odoo14_addon_ssi_telegram-14.0.1.4.0.dist-info/METADATA
odoo14_addon_ssi_telegram-14.0.1.4.0.dist-info/WHEEL
odoo14_addon_ssi_telegram-14.0.1.4.0.dist-info/top_level.txt
odoo14_addon_ssi_telegram-14.0.1.4.0.dist-info/RECORD
